{
    "ToCountry": "US",
    "ToState": "NY",
    "SmsMessageSid": "SMe34670bedf524e6f096a2318c9a967b5",
    "NumMedia": "0",
    "ToCity": "",
    "FromZip": "77705",
    "SmsSid": "SMe34670bedf524e6f096a2318c9a967b5",
    "FromState": "TX",
    "SmsStatus": "received",
    "FromCity": "BEAUMONT",
    "Body": "Heyyo",
    "FromCountry": "US",
    "To": "+15185353194",
    "MessagingServiceSid": "MG23863006ce06dba09759177ba470bcf5",
    "ToZip": "",
    "NumSegments": "1",
    "ReferralNumMedia": "0",
    "MessageSid": "SMe34670bedf524e6f096a2318c9a967b5",
    "AccountSid": "ACf173a74fa920b7f50f08424b274aa75b",
    "From": "+14097912533",
    "ApiVersion": "2010-04-01"
  }